{
  "dashboard": {
    "id": null,
    "uid": "system-metrics",
    "title": "MLOps System Metrics",
    "description": "System monitoring for MLOps sentiment analysis API",
    "tags": ["system", "monitoring", "mlops"],
    "timezone": "browser",
    "schemaVersion": 30,
    "version": 1,
    "panels": [
      {
        "id": 1,
        "title": "CPU Usage",
        "type": "stat",
        "targets": [
          {
            "expr": "100 - (avg(rate(node_cpu_seconds_total{mode=\"idle\"}[5m])) * 100)",
            "legendFormat": "CPU Usage %",
            "refId": "A"
          }
        ],
        "fieldConfig": {
          "defaults": {
            "unit": "percent",
            "max": 100,
            "min": 0,
            "thresholds": {
              "steps": [
                {"color": "green", "value": null},
                {"color": "yellow", "value": 70},
                {"color": "red", "value": 90}
              ]
            }
          }
        },
        "gridPos": {"h": 8, "w": 6, "x": 0, "y": 0}
      },
      {
        "id": 2,
        "title": "Memory Usage",
        "type": "stat",
        "targets": [
          {
            "expr": "(1 - (node_memory_MemAvailable_bytes / node_memory_MemTotal_bytes)) * 100",
            "legendFormat": "Memory Usage %",
            "refId": "A"
          }
        ],
        "fieldConfig": {
          "defaults": {
            "unit": "percent",
            "max": 100,
            "min": 0,
            "thresholds": {
              "steps": [
                {"color": "green", "value": null},
                {"color": "yellow", "value": 70},
                {"color": "red", "value": 85}
              ]
            }
          }
        },
        "gridPos": {"h": 8, "w": 6, "x": 6, "y": 0}
      },
      {
        "id": 3,
        "title": "Disk Usage",
        "type": "stat",
        "targets": [
          {
            "expr": "100 - ((node_filesystem_avail_bytes{mountpoint=\"/\"} * 100) / node_filesystem_size_bytes{mountpoint=\"/\"})",
            "legendFormat": "Disk Usage %",
            "refId": "A"
          }
        ],
        "fieldConfig": {
          "defaults": {
            "unit": "percent",
            "max": 100,
            "min": 0,
            "thresholds": {
              "steps": [
                {"color": "green", "value": null},
                {"color": "yellow", "value": 80},
                {"color": "red", "value": 90}
              ]
            }
          }
        },
        "gridPos": {"h": 8, "w": 6, "x": 12, "y": 0}
      },
      {
        "id": 4,
        "title": "Network I/O",
        "type": "graph",
        "targets": [
          {
            "expr": "rate(node_network_receive_bytes_total[5m])",
            "legendFormat": "{{device}} RX",
            "refId": "A"
          },
          {
            "expr": "rate(node_network_transmit_bytes_total[5m])",
            "legendFormat": "{{device}} TX",
            "refId": "B"
          }
        ],
        "fieldConfig": {
          "defaults": {
            "unit": "Bps"
          }
        },
        "gridPos": {"h": 8, "w": 6, "x": 18, "y": 0}
      },
      {
        "id": 5,
        "title": "API Request Rate",
        "type": "graph",
        "targets": [
          {
            "expr": "rate(http_requests_total[5m])",
            "legendFormat": "{{method}} {{handler}}",
            "refId": "A"
          }
        ],
        "fieldConfig": {
          "defaults": {
            "unit": "reqps"
          }
        },
        "gridPos": {"h": 8, "w": 12, "x": 0, "y": 8}
      },
      {
        "id": 6,
        "title": "API Error Rate",
        "type": "graph", 
        "targets": [
          {
            "expr": "rate(http_requests_total{status=~\"4..|5..\"}[5m]) / rate(http_requests_total[5m]) * 100",
            "legendFormat": "Error Rate %",
            "refId": "A"
          }
        ],
        "fieldConfig": {
          "defaults": {
            "unit": "percent",
            "max": 100,
            "min": 0
          }
        },
        "gridPos": {"h": 8, "w": 12, "x": 12, "y": 8}
      },
      {
        "id": 7,
        "title": "Model Inference Time",
        "type": "graph",
        "targets": [
          {
            "expr": "histogram_quantile(0.95, rate(prediction_duration_seconds_bucket[5m]))",
            "legendFormat": "95th percentile",
            "refId": "A"
          },
          {
            "expr": "histogram_quantile(0.50, rate(prediction_duration_seconds_bucket[5m]))",
            "legendFormat": "50th percentile", 
            "refId": "B"
          }
        ],
        "fieldConfig": {
          "defaults": {
            "unit": "s"
          }
        },
        "gridPos": {"h": 8, "w": 12, "x": 0, "y": 16}
      },
      {
        "id": 8,
        "title": "Model Confidence Scores",
        "type": "graph",
        "targets": [
          {
            "expr": "histogram_quantile(0.95, rate(prediction_confidence_bucket[5m]))",
            "legendFormat": "95th percentile confidence",
            "refId": "A"
          },
          {
            "expr": "histogram_quantile(0.50, rate(prediction_confidence_bucket[5m]))",
            "legendFormat": "50th percentile confidence",
            "refId": "B"
          }
        ],
        "fieldConfig": {
          "defaults": {
            "unit": "short",
            "max": 1,
            "min": 0
          }
        },
        "gridPos": {"h": 8, "w": 12, "x": 12, "y": 16}
      }
    ],
    "time": {
      "from": "now-1h",
      "to": "now"
    },
    "refresh": "5s"
  }
}